[
{
    "id": "1",
    "title": "Diet Guide",
    "session": [
    {
      "id": 1,
      "question": "Have you eaten vegetables today?",
      "type": "open"
    },
    {
      "id": "2",
      "question": "Any junk food?",
      "type": "vital"
    }
    ]
},
{
    "id": "2",
    "title": "Heart Monitoring",
    "session": [
    {
      "id": 1,
      "question": "What is your blood pressure?",
      "type": "open"
    },
    {
      "id": "2",
      "question": "What is your pulse rate?",
      "type": "vital"
    }
    ]
},
{
    "id": "3",
    "title": "Daily Caloric Intake",
    "session": [
    {
        "id": 1,
        "question": "Did you meet your goal of 1750-2000 calories today?",
        "type": "multi",
        "possibleAnswers":[
            {
                "0": "Yes",
                "nextQuestion": 2
            },
            {
                "1": "No",
                "nextQuestion": 5
            }
        ]
    },
    {
        "id": 2,
        "question": "Were you able to get them through 5 small meals?",
        "type": "multi",
        "possibleAnswers":[
            {
                "0": "Yes",
                "nextQuestion": 3
            },
            {
                "1": "No",
                "nextQuestion": 4
            }
        ]
    },
    {
        "id": 3,
        "question": "Excellent! Keep up the great work!",
        "type": "general",
        "possibleAnswers":[],
        "nextQuestion": -1
    },
    {
        "id": 4,
        "question": "It's a great start to hit your target calorie count.  The best way to take digest those calories is through 5 small meals.  If you're eating larger meals, you might be taking in too many calories at once cause your body to store fat.  If you are snacking throughout the day, you probably aren't getting the proper nutrition to reach 2000 calories in a healthy manor ",
        "type": "general",
        "possibleAnswers":[],
        "nextQuestion": -1
    },
    {
        "id": 5,
        "question": "Did you go over 2000 calories or under 1750?",
        "type": "multi",
        "possibleAnswers":[
            {
                "0": "Over 2000",
                "nextQuestion": 6
            },
            {
                "1": "Under 1750",
                "nextQuestion": 6
            }
        ]
    },
    {
        "id": 6,
        "question": "In order to reach your goal weight, it's critical that you maintain a steady diet of 1750-2000 calories a day!",
        "type": "multi",
        "possibleAnswers":[],
        "nextQuestion": -1
    }
    ]
}

]